LICENSE
MANIFEST.in
README.txt
setup.cfg
setup.py
pyonedrive/__init__.py
pyonedrive/live_auth.py
pyonedrive/py_onedrive.py
pyonedrive/version.py
pyonedrive.egg-info/PKG-INFO
pyonedrive.egg-info/SOURCES.txt
pyonedrive.egg-info/dependency_links.txt
pyonedrive.egg-info/not-zip-safe
pyonedrive.egg-info/pbr.json
pyonedrive.egg-info/requires.txt
pyonedrive.egg-info/top_level.txt