Metadata-Version: 1.1
Name: pyonedrive
Version: 1.2
Summary: Onedrive REST api client
Home-page: https://github.com/cogniteevpyonedrive
Author: Tony Sanchez
Author-email: mail.tsanchez@gmail.com
License: Apache license version 2.0
Download-URL: https://github.com/cogniteev/pyonedrive/tarball/v1.2
Platform: OS Independent
Classifier: Programming Language :: Python
Classifier: Programming Language :: Python :: 2.7
Classifier: Intended Audience :: Developers
Classifier: License :: OSI Approved :: Apache Software License
Classifier: Operating System :: OS Independent
Classifier: Topic :: Software Development :: Libraries :: Python Modules
Classifier: Environment :: Web Environment
Classifier: Development Status :: 4 - Beta
